loglan_db/__init__.py
loglan_db/model.py
loglan_db/model_export.py
loglan_db/model_init.py
loglan_db/model_db/__init__.py
loglan_db/model_db/base_author.py
loglan_db/model_db/base_connect_tables.py
loglan_db/model_db/base_definition.py
loglan_db/model_db/base_event.py
loglan_db/model_db/base_key.py
loglan_db/model_db/base_setting.py
loglan_db/model_db/base_syllable.py
loglan_db/model_db/base_type.py
loglan_db/model_db/base_word.py
loglan_db/model_db/base_word_source.py
loglan_db/model_db/base_word_spell.py
loglan_db/model_db/addons/__init__.py
loglan_db/model_db/addons/addon_key_getter.py
loglan_db/model_db/addons/addon_word_getter.py
loglan_db/model_db/addons/addon_word_linker.py
loglan_db/model_db/addons/addon_word_sourcer.py
loglan_db/model_html/__init__.py
loglan_db/model_html/html_definition.py
loglan_db/model_html/html_word.py
Loglan_DB-0.1.21.dist-info/LICENSE
Loglan_DB-0.1.21.dist-info/METADATA
Loglan_DB-0.1.21.dist-info/WHEEL
Loglan_DB-0.1.21.dist-info/top_level.txt
Loglan_DB-0.1.21.dist-info/RECORD
