Metadata-Version: 2.1
Name: Loglan-DB
Version: 0.1.21
Summary: Loglan Dictionary Database Model for SQLAlchemy
Home-page: https://github.com/torrua/loglan_db
Download-URL: https://github.com/torrua/loglan_db/archive/v0.1.21.tar.gz
Author: torrua
Author-email: torrua@gmail.com
License: MIT
Keywords: Loglan,Dictionary,Database,Model,LOD
Classifier: Development Status :: 5 - Production/Stable
Classifier: Intended Audience :: Developers
Classifier: Intended Audience :: Science/Research
Classifier: Framework :: Flask
Classifier: Topic :: Database
Classifier: License :: OSI Approved :: MIT License
Classifier: Programming Language :: Python :: 3.8
Classifier: Programming Language :: Python :: 3.9
Classifier: Programming Language :: Python :: 3.10
Requires-Python: >=3.8
License-File: LICENSE
Requires-Dist: flask
Requires-Dist: sqlalchemy
Requires-Dist: flask-sqlalchemy
Requires-Dist: psycopg2
